{
  "word": "geblak",
  "authenticated": true,
  "entries": [
    {
      "id": "24946",
      "nama": "geb.lak",
      "nomor": "",
      "makna": [
        {
          "nomor": "1",
          "kelasKata": [
            {
              "kode": "v",
              "nama": "Verba",
              "tipe": "kelas_kata"
            }
          ],
          "definisi": "telentang",
          "contoh": []
        }
      ],
      "terkait": {
        "kataTurunan": [
          "menggeblak"
        ],
        "gabunganKata": [],
        "peribahasa": [],
        "idiom": []
      }
    }
  ]
}