{
  "word": "gintir",
  "authenticated": true,
  "entries": [
    {
      "id": "94372",
      "nama": "gin.tir",
      "nomor": "",
      "makna": [
        {
          "nomor": "1",
          "kelasKata": [
            {
              "kode": "v",
              "nama": "Verba",
              "tipe": "kelas_kata"
            }
          ],
          "definisi": "pilin",
          "contoh": []
        }
      ],
      "terkait": {
        "kataTurunan": [
          "gintiran",
          "menggintir"
        ],
        "gabunganKata": [],
        "peribahasa": [],
        "idiom": []
      }
    },
    {
      "id": "242448",
      "nama": "gin.tir",
      "nomor": "",
      "makna": [
        {
          "nomor": "1",
          "kelasKata": [
            {
              "kode": "n",
              "nama": "Nomina",
              "tipe": "kelas_kata"
            },
            {
              "kode": "Us",
              "nama": "Using",
              "tipe": "lainnya"
            }
          ],
          "definisi": "ritual pengasihan dengan media cabai atau merica yang diputar-putar dengan jari telunjuk dan jempol hingga pecah sambil membaca mantra, dilakukan oleh laki-laki kepada perempuan yang disukai",
          "contoh": []
        }
      ],
      "terkait": {
        "kataTurunan": [],
        "gabunganKata": [],
        "peribahasa": [],
        "idiom": []
      }
    },
    {
      "id": "249689",
      "nama": "gin.tir",
      "nomor": "2",
      "makna": [
        {
          "nomor": "1",
          "kelasKata": [
            {
              "kode": "v",
              "nama": "Verba",
              "tipe": "kelas_kata"
            },
            {
              "kode": "Sd",
              "nama": "Sunda",
              "tipe": "bahasa"
            }
          ],
          "definisi": "menggiling padi dengan kayu bergerigi",
          "contoh": []
        }
      ],
      "terkait": {
        "kataTurunan": [],
        "gabunganKata": [],
        "peribahasa": [],
        "idiom": []
      }
    }
  ]
}