{
  "word": "filial",
  "authenticated": true,
  "entries": [
    {
      "id": "23139",
      "nama": "fi.li.al",
      "nomor": "",
      "makna": [
        {
          "nomor": "1",
          "kelasKata": [
            {
              "kode": "n",
              "nama": "Nomina",
              "tipe": "kelas_kata"
            }
          ],
          "definisi": "bagian perusahaan yang berkedudukan tersendiri (terutama tentang perusahaan perbankan dan pertokoan); anak perusahaan",
          "contoh": []
        },
        {
          "nomor": "2",
          "kelasKata": [
            {
              "kode": "n",
              "nama": "Nomina",
              "tipe": "kelas_kata"
            }
          ],
          "definisi": "cabang (perusahaan, sekolah, dan sebagainya)",
          "contoh": []
        },
        {
          "nomor": "3",
          "kelasKata": [
            {
              "kode": "n",
              "nama": "Nomina",
              "tipe": "kelas_kata"
            },
            {
              "kode": "Bio",
              "nama": "Biologi",
              "tipe": "bidang_subjek"
            }
          ],
          "definisi": "hasil pembastaran",
          "contoh": []
        }
      ]
    }
  ]
}