{
  "word": "watun",
  "authenticated": true,
  "entries": [
    {
      "id": "91205",
      "nama": "wa.tun",
      "nomor": "",
      "makna": [
        {
          "nomor": "1",
          "kelasKata": [
            {
              "kode": "n",
              "nama": "Nomina",
              "tipe": "kelas_kata"
            },
            {
              "kode": "Bjr",
              "nama": "Banjar",
              "tipe": "bahasa"
            }
          ],
          "definisi": "bagian lantai yang ditinggikan (pada rumah Banjar)",
          "contoh": []
        }
      ],
      "terkait": {
        "kataTurunan": [
          "berwatun"
        ],
        "gabunganKata": [],
        "peribahasa": [],
        "idiom": []
      }
    }
  ]
}