{
  "word": "latihan tempur",
  "authenticated": true,
  "entries": [
    {
      "id": "47298",
      "nama": "latihan tempur",
      "nomor": "",
      "makna": [
        {
          "nomor": "1",
          "kelasKata": [
            {
              "kode": "Mil",
              "nama": "Kemiliteran",
              "tipe": "lainnya"
            }
          ],
          "definisi": "latihan teknik pertempuran",
          "contoh": []
        }
      ],
      "rootWord": "latihlatihan"
    }
  ]
}