{"word":"layut","authenticated":true,"entries":[{"id":"47607","nama":"la.yut","nomor":"1","makna":[{"nomor":"1","kelasKata":[{"kode":"v","nama":"Verba","tipe":"kelas_kata"}],"definisi":"melentur","contoh":[]}],"etimologi":{"text":"[Jawa Kuno layut 'cara khusus bermain gamelan (bagian tertentu dalam melodi)']","languages":["Jawa Kuno"]},"terkait":{"kataTurunan":["melayut"],"gabunganKata":[],"peribahasa":[],"idiom":[]}},{"id":"47609","nama":"la.yut","nomor":"2","makna":[{"nomor":"1","kelasKata":[{"kode":"v","nama":"Verba","tipe":"kelas_kata"}],"definisi":"melayut","contoh":[]}],"etimologi":{"text":"[Jawa Kuno layut 'cara khusus bermain gamelan (bagian tertentu dalam melodi)']","languages":["Jawa Kuno"]},"terkait":{"kataTurunan":["melayut"],"gabunganKata":[],"peribahasa":[],"idiom":[]}}]}