{
  "word": "lebai",
  "authenticated": true,
  "entries": [
    {
      "id": "47625",
      "nama": "le.bai",
      "nomor": "1",
      "makna": [
        {
          "nomor": "1",
          "kelasKata": [
            {
              "kode": "n",
              "nama": "Nomina",
              "tipe": "kelas_kata"
            }
          ],
          "definisi": "pegawai masjid atau orang yang mengurus suatu pekerjaan yang bertalian dengan agama Islam di dusun (kampung)",
          "contoh": []
        }
      ],
      "terkait": {
        "kataTurunan": [
          "kelebaian"
        ],
        "gabunganKata": [
          "lebai malang",
          "lebai penghulu"
        ],
        "peribahasa": [],
        "idiom": []
      }
    },
    {
      "id": "109315",
      "nama": "le.bai",
      "nomor": "2",
      "makna": [
        {
          "nomor": "1",
          "kelasKata": [
            {
              "kode": "a",
              "nama": "Adjektiva",
              "tipe": "kelas_kata"
            },
            {
              "kode": "cak",
              "nama": "Cakapan",
              "tipe": "kelas_kata"
            }
          ],
          "definisi": "berlebih-lebihan dalam mengekspresikan sesuatu; laku lajak",
          "contoh": [
            {
              "nomor": 2,
              "teks": "orang itu -- sekali"
            }
          ]
        }
      ],
      "terkait": {
        "kataTurunan": [
          "kelebaian"
        ],
        "gabunganKata": [],
        "peribahasa": [],
        "idiom": []
      }
    }
  ]
}