{
  "word": "tapak kuda",
  "authenticated": true,
  "entries": [
    {
      "id": "82657",
      "nama": "ta.pak ku.da",
      "nomor": "",
      "makna": [
        {
          "nomor": "1",
          "kelasKata": [
            {
              "kode": "n",
              "nama": "Nomina",
              "tipe": "kelas_kata"
            }
          ],
          "definisi": "terna menjalar, tumbuh dekat pantai, batangnya liat dan panjang, daunnya lebat, digunakan sebagai obat untuk mematangkan bisul, akarnya direbus, air rebusan dibuat obat sebagai pencuci kaki penderita beri-beri; katang-katang〔Ipomoea pescaprae〕",
          "contoh": []
        }
      ],
      "terkait": {
        "kataTurunan": [],
        "gabunganKata": [],
        "peribahasa": [],
        "idiom": []
      }
    }
  ]
}