{
  "word": "teknologi medis",
  "authenticated": true,
  "entries": [
    {
      "id": "83816",
      "nama": "teknologi medis",
      "nomor": "",
      "makna": [
        {
          "nomor": "1",
          "kelasKata": [],
          "definisi": "ilmu kedokteran yang menggunakan peralatan serta prosedur tertentu untuk membantu menemukan penyebab penyakit serta membantu pengobatannya",
          "contoh": []
        }
      ],
      "rootWord": "teknologi",
      "terkait": {
        "kataTurunan": [],
        "gabunganKata": [],
        "peribahasa": [],
        "idiom": []
      }
    }
  ]
}