{
  "word": "terpilu",
  "authenticated": true,
  "entries": [
    {
      "id": "102094",
      "nama": "ter.pi.lu",
      "nomor": "",
      "makna": [
        {
          "nomor": "1",
          "kelasKata": [
            {
              "kode": "a",
              "nama": "Adjektiva",
              "tipe": "kelas_kata"
            }
          ],
          "definisi": "paling pilu",
          "contoh": [
            {
              "nomor": 2,
              "teks": "rintik- rintik hujan dapat menciptakan awan yang ~"
            }
          ]
        }
      ],
      "rootWord": "pilu",
      "terkait": {
        "kataTurunan": [],
        "gabunganKata": [],
        "peribahasa": [],
        "idiom": []
      }
    }
  ]
}