{
  "word": "jurus",
  "authenticated": true,
  "entries": [
    {
      "id": "35345",
      "nama": "ju.rus",
      "nomor": "1",
      "makna": [
        {
          "nomor": "1",
          "kelasKata": [],
          "definisi": "⇢ Tesaurus prakategorial berjurus-jurus, sejurus",
          "contoh": []
        }
      ],
      "terkait": {
        "kataTurunan": [
          "berjurus-jurus",
          "sejurus",
          "berjurus",
          "jurusan",
          "menjurus",
          "menjuruskan",
          "penjurus",
          "penjurusan"
        ],
        "gabunganKata": [
          "jurus ampuh",
          "jurus kepepet",
          "jurus mabuk",
          "jurus pamungkas",
          "jurus sesar",
          "jurus silat"
        ],
        "peribahasa": [],
        "idiom": [
          "jurus jitu"
        ]
      }
    },
    {
      "id": "35348",
      "nama": "ju.rus",
      "nomor": "2",
      "makna": [
        {
          "nomor": "1",
          "kelasKata": [
            {
              "kode": "n",
              "nama": "Nomina",
              "tipe": "kelas_kata"
            }
          ],
          "definisi": "arah yang lurus (langsung)",
          "contoh": []
        },
        {
          "nomor": "2",
          "kelasKata": [
            {
              "kode": "n",
              "nama": "Nomina",
              "tipe": "kelas_kata"
            }
          ],
          "definisi": "bagian sikap (tegak dan sebagainya) dalam permainan pencak silat",
          "contoh": []
        }
      ],
      "terkait": {
        "kataTurunan": [
          "berjurus",
          "jurusan",
          "menjurus",
          "menjuruskan",
          "penjurus",
          "penjurusan"
        ],
        "gabunganKata": [
          "jurus ampuh",
          "jurus kepepet",
          "jurus mabuk",
          "jurus pamungkas",
          "jurus sesar",
          "jurus silat"
        ],
        "peribahasa": [],
        "idiom": [
          "jurus jitu"
        ]
      }
    }
  ]
}