{
  "word": "penyemaian awan",
  "authenticated": true,
  "entries": [
    {
      "id": "105852",
      "nama": "penyemaian awan",
      "nomor": "",
      "makna": [
        {
          "nomor": "1",
          "kelasKata": [
            {
              "kode": "Hidm",
              "nama": "Hidrometeorologi",
              "tipe": "lainnya"
            }
          ],
          "definisi": "modifikasi proses fisis yang terdapat dalam awan alami dengan cara penyempurnaan awan dengan bahan penyemai",
          "contoh": []
        }
      ],
      "rootWord": "semaipenyemaian",
      "terkait": {
        "kataTurunan": [],
        "gabunganKata": [],
        "peribahasa": [],
        "idiom": []
      }
    }
  ]
}