{
  "word": "penyenaraian",
  "authenticated": true,
  "entries": [
    {
      "id": "102348",
      "nama": "pe.nye.na.rai.an",
      "nomor": "",
      "makna": [
        {
          "nomor": "1",
          "kelasKata": [
            {
              "kode": "n",
              "nama": "Nomina",
              "tipe": "kelas_kata"
            },
            {
              "kode": "Komp",
              "nama": "Komputer",
              "tipe": "lainnya"
            }
          ],
          "definisi": "pembuatan daftar",
          "contoh": []
        }
      ],
      "rootWord": "senarai",
      "terkait": {
        "kataTurunan": [],
        "gabunganKata": [
          "penyenaraian program"
        ],
        "peribahasa": [],
        "idiom": []
      }
    }
  ]
}