{
  "word": "perang budaya",
  "authenticated": true,
  "entries": [
    {
      "id": "108371",
      "nama": "perang budaya",
      "nomor": "",
      "makna": [
        {
          "nomor": "1",
          "kelasKata": [],
          "definisi": "cara untuk mengubah perilaku, nilai, dan cita rasa suatu masyarakat, biasanya dilakukan melalui media populer dan dilakukan secara halus, tidak terang-terangan",
          "contoh": []
        }
      ],
      "rootWord": "perang",
      "terkait": {
        "kataTurunan": [],
        "gabunganKata": [],
        "peribahasa": [],
        "idiom": []
      }
    }
  ]
}