{
  "word": "peria putih",
  "authenticated": true,
  "entries": [
    {
      "id": "62493",
      "nama": "peria putih",
      "nomor": "",
      "makna": [
        {
          "nomor": "1",
          "kelasKata": [],
          "definisi": "buah peria yang rasanya tidak terlampau pahit, buahnya besar dan berwarna putih",
          "contoh": []
        }
      ],
      "rootWord": "peria",
      "terkait": {
        "kataTurunan": [],
        "gabunganKata": [],
        "peribahasa": [],
        "idiom": []
      }
    }
  ]
}