{
  "word": "peruangan",
  "authenticated": true,
  "entries": [
    {
      "id": "88752",
      "nama": "per.u.ang.an",
      "nomor": "",
      "makna": [
        {
          "nomor": "1",
          "kelasKata": [
            {
              "kode": "n",
              "nama": "Nomina",
              "tipe": "kelas_kata"
            }
          ],
          "definisi": "perihal yang berhubungan dengan uang; keadaan dan urusan uang",
          "contoh": [
            {
              "nomor": 2,
              "teks": "kekacauan perdagangan dan ~ cukup merepotkan negara-negara berkembang"
            }
          ]
        }
      ],
      "rootWord": "uang"
    }
  ]
}