{"word":"ponti","authenticated":true,"entries":[{"id":"230496","nama":"pon.ti","nomor":"1","makna":[{"nomor":"1","kelasKata":[{"kode":"v","nama":"Verba","tipe":"kelas_kata"},{"kode":"Kj","nama":"Konjo","tipe":"lainnya"}],"definisi":"menjampi sambil memijat bagian tubuh orang yang sakit","contoh":[]}]},{"id":"100363","nama":"Pon.ti","nomor":"2","makna":[{"nomor":"1","kelasKata":[{"kode":"n","nama":"Nomina","tipe":"kelas_kata"}],"definisi":"suku bangsa yang mendiami daerah Kabupaten Sanggau, Provinsi Kalimantan Barat","contoh":[]}]}]}