{
  "word": "profil zat gizi",
  "authenticated": true,
  "entries": [
    {
      "id": "106264",
      "nama": "profil zat gizi",
      "nomor": "",
      "makna": [
        {
          "nomor": "1",
          "kelasKata": [
            {
              "kode": "Gz",
              "nama": "Ilmu Gizi",
              "tipe": "lainnya"
            }
          ],
          "definisi": "komposisi gizi dari pangan tertentu",
          "contoh": []
        }
      ],
      "rootWord": "profil"
    }
  ]
}