{"word":"renung","authenticated":true,"entries":[{"id":"68827","nama":"re.nung","nomor":"1","makna":[{"nomor":"1","kelasKata":[],"definisi":"⇢ Tesaurus prakategorial merenung, merenungi","contoh":[]}],"terkait":{"kataTurunan":["merenung","merenungi","merenungkan","perenung","perenungan","renungan"],"gabunganKata":[],"peribahasa":[],"idiom":[]}},{"id":"68830","nama":"re.nung","nomor":"2","makna":[{"nomor":"1","kelasKata":[],"definisi":"⇢ Tesaurus prakategorial merenung, merenungi, merenungkan, perenung, perenungan, renungan","contoh":[]}],"terkait":{"kataTurunan":["merenung","merenungi","merenungkan","perenung","perenungan","renungan"],"gabunganKata":[],"peribahasa":[],"idiom":[]}}]}