{
  "word": "kerah draperi",
  "authenticated": true,
  "entries": [
    {
      "id": "40146",
      "nama": "kerah draperi",
      "nomor": "2",
      "makna": [
        {
          "nomor": "1",
          "kelasKata": [
            {
              "kode": "Tbs",
              "nama": "Tata Busana",
              "tipe": "lainnya"
            }
          ],
          "definisi": "leher baju dengan biku-biku lembut yang dapat ditata dengan berbagai cara",
          "contoh": []
        }
      ],
      "rootWord": "kerah²",
      "terkait": {
        "kataTurunan": [],
        "gabunganKata": [],
        "peribahasa": [],
        "idiom": []
      }
    }
  ]
}