{
  "word": "mantel tudung",
  "authenticated": true,
  "entries": [
    {
      "id": "169473",
      "nama": "mantel tudung",
      "nomor": "",
      "makna": [
        {
          "nomor": "1",
          "kelasKata": [
            {
              "kode": "Tbs",
              "nama": "Tata Busana",
              "tipe": "lainnya"
            }
          ],
          "definisi": "mantel tanpa lengan dengan potongan pas di bagian leher dan menggantung di bahu",
          "contoh": []
        }
      ],
      "rootWord": "mantel"
    }
  ]
}