{
  "word": "masai",
  "authenticated": true,
  "entries": [
    {
      "id": "52500",
      "nama": "ma.sai",
      "nomor": "",
      "makna": [
        {
          "nomor": "1",
          "kelasKata": [],
          "definisi": "lihat kusut",
          "contoh": []
        }
      ],
      "terkait": {
        "kataTurunan": [
          "memasai"
        ],
        "gabunganKata": [],
        "peribahasa": [],
        "idiom": []
      }
    },
    {
      "id": "218984",
      "nama": "ma.sai",
      "nomor": "2",
      "makna": [
        {
          "nomor": "1",
          "kelasKata": [
            {
              "kode": "n",
              "nama": "Nomina",
              "tipe": "kelas_kata"
            },
            {
              "kode": "Mr",
              "nama": "Mandar",
              "tipe": "lainnya"
            }
          ],
          "definisi": "pohon pisang yang menguning batang dan daunnya, karena terkena penyakit",
          "contoh": []
        }
      ],
      "terkait": {
        "kataTurunan": [],
        "gabunganKata": [],
        "peribahasa": [],
        "idiom": []
      }
    }
  ]
}