{
  "word": "melonceng",
  "authenticated": true,
  "entries": [
    {
      "id": "50111",
      "nama": "me.lon.ceng",
      "nomor": "",
      "makna": [
        {
          "nomor": "1",
          "kelasKata": [
            {
              "kode": "v",
              "nama": "Verba",
              "tipe": "kelas_kata"
            }
          ],
          "definisi": "membunyikan lonceng",
          "contoh": []
        }
      ],
      "rootWord": "lonceng",
      "terkait": {
        "kataTurunan": [],
        "gabunganKata": [],
        "peribahasa": [],
        "idiom": []
      }
    }
  ]
}