{
  "word": "menebah",
  "authenticated": true,
  "entries": [
    {
      "id": "83355",
      "nama": "me.ne.bah",
      "nomor": "1",
      "makna": [
        {
          "nomor": "1",
          "kelasKata": [
            {
              "kode": "v",
              "nama": "Verba",
              "tipe": "kelas_kata"
            }
          ],
          "definisi": "memukul sesuatu dengan barang yang pipih: ombak memukul pantai",
          "contoh": [
            {
              "nomor": 2,
              "teks": "~ air dengan dayung"
            },
            {
              "nomor": 4,
              "teks": "~ kasur"
            },
            {
              "nomor": 6,
              "teks": "ombak ~ pantai"
            }
          ]
        },
        {
          "nomor": "2",
          "kelasKata": [
            {
              "kode": "v",
              "nama": "Verba",
              "tipe": "kelas_kata"
            },
            {
              "kode": "Olr",
              "nama": "Olahraga",
              "tipe": "lainnya"
            }
          ],
          "definisi": "memukul dengan memegang tangan bagian depan",
          "contoh": []
        },
        {
          "nomor": "3",
          "kelasKata": [
            {
              "kode": "v",
              "nama": "Verba",
              "tipe": "kelas_kata"
            },
            {
              "kode": "Olr",
              "nama": "Olahraga",
              "tipe": "lainnya"
            }
          ],
          "definisi": "menebahkan",
          "contoh": []
        }
      ],
      "rootWord": "tebah¹",
      "terkait": {
        "kataTurunan": [],
        "gabunganKata": [
          "menebah dada"
        ],
        "peribahasa": [],
        "idiom": []
      }
    }
  ]
}