{
  "word": "menggericau",
  "authenticated": true,
  "entries": [
    {
      "id": "26441",
      "nama": "meng.ge.ri.cau",
      "nomor": "",
      "makna": [
        {
          "nomor": "1",
          "kelasKata": [
            {
              "kode": "v",
              "nama": "Verba",
              "tipe": "kelas_kata"
            }
          ],
          "definisi": "berbunyi keras-keras dan berulang-ulang (seperti bunyi burung)",
          "contoh": []
        }
      ],
      "rootWord": "gericau",
      "terkait": {
        "kataTurunan": [],
        "gabunganKata": [],
        "peribahasa": [],
        "idiom": []
      }
    }
  ]
}