{
  "word": "menyukat",
  "authenticated": true,
  "entries": [
    {
      "id": "79439",
      "nama": "me.nyu.kat",
      "nomor": "1",
      "makna": [
        {
          "nomor": "1",
          "kelasKata": [
            {
              "kode": "v",
              "nama": "Verba",
              "tipe": "kelas_kata"
            }
          ],
          "definisi": "menakar (dengan sukat)",
          "contoh": []
        }
      ],
      "rootWord": "sukat¹",
      "terkait": {
        "kataTurunan": [],
        "gabunganKata": [],
        "peribahasa": [
          "bagai menyukat anak ayam",
          "bagai menyukat belut",
          "menyukat penuh sudah"
        ],
        "idiom": [],
        "peribahasa_dan_makna": [
          {
            "peribahasa": "bagai menyukat anak ayam",
            "makna": "Mencoba mengatur atau mengendalikan sesuatu yang sangat sulit diatur atau dikendalikan."
          },
          {
            "peribahasa": "bagai menyukat belut",
            "makna": "Mencoba mengendalikan atau mengukur sesuatu yang sangat licin atau sulit dipegang."
          },
          {
            "peribahasa": "menyukat penuh sudah",
            "makna": "Sesuatu telah mencapai batas maksimal atau kapasitas penuh."
          }
        ]
      }
    }
  ]
}