{
  "word": "minyak media",
  "authenticated": true,
  "entries": [
    {
      "id": "54599",
      "nama": "minyak media",
      "nomor": "",
      "makna": [
        {
          "nomor": "1",
          "kelasKata": [
            {
              "kode": "Pet",
              "nama": "Petrologi dan Migas",
              "tipe": "lainnya"
            }
          ],
          "definisi": "selingan antara minyak tanah dan minyak diesel, digunakan dalam lampu sinyal, media absorpsi dalam proses perolehan bensin, media untuk bahan pemberantas serangga dan bahan penyemprot",
          "contoh": []
        }
      ],
      "rootWord": "minyak"
    }
  ]
}