{
  "word": "mulat sarira hangrasa wani",
  "authenticated": true,
  "entries": [
    {
      "id": "97666",
      "nama": "mulat sarira hangrasa wani",
      "nomor": "",
      "makna": [
        {
          "nomor": "1",
          "kelasKata": [
            {
              "kode": "ukp",
              "nama": "Ungkapan",
              "tipe": "kelas_kata"
            },
            {
              "kode": "Jw",
              "nama": "Jawa",
              "tipe": "bahasa"
            }
          ],
          "definisi": "berani mewawas diri; berani melakukan introspeksi",
          "contoh": []
        }
      ]
    }
  ]
}