{
  "word": "hak bersama",
  "authenticated": true,
  "entries": [
    {
      "id": "28177",
      "nama": "hak bersama",
      "nomor": "1",
      "makna": [
        {
          "nomor": "1",
          "kelasKata": [],
          "definisi": "hak yang dimiliki oleh beberapa orang terhadap suatu objek",
          "contoh": []
        }
      ],
      "rootWord": "hak¹",
      "terkait": {
        "kataTurunan": [],
        "gabunganKata": [],
        "peribahasa": [],
        "idiom": []
      }
    }
  ]
}