{
  "word": "hilir",
  "authenticated": true,
  "entries": [
    {
      "id": "29640",
      "nama": "hi.lir",
      "nomor": "",
      "makna": [
        {
          "nomor": "1",
          "kelasKata": [
            {
              "kode": "n",
              "nama": "Nomina",
              "tipe": "kelas_kata"
            }
          ],
          "definisi": "bagian sungai sebelah muara",
          "contoh": [
            {
              "nomor": 2,
              "teks": "sampai ke -- sungai"
            }
          ]
        },
        {
          "nomor": "2",
          "kelasKata": [
            {
              "kode": "n",
              "nama": "Nomina",
              "tipe": "kelas_kata"
            }
          ],
          "definisi": "daerah sepanjang bagian muara sungai (daerah pesisir)",
          "contoh": [
            {
              "nomor": 2,
              "teks": "orang --"
            }
          ]
        }
      ],
      "terkait": {
        "kataTurunan": [
          "berhilir",
          "berhiliran",
          "menghilir",
          "menghiliri",
          "menghilirkan",
          "penghiliran",
          "sehilir",
          "terhilir"
        ],
        "gabunganKata": [
          "hilir angin",
          "hilir malam",
          "hilir mudik",
          "hilir sungai"
        ],
        "peribahasa": [
          "belum tentu hilir mudiknya",
          "bergalah hilir tertawa buaya, bersuluh di bulan terang tertawa harimau",
          "berkata di bawah-bawah mandi di hilir-hilir",
          "berkayuh sambil ke hilir",
          "hilir malam mudik tak singgah, daun nipah dikatakan daun abu",
          "ikan di hulu, tuba di hilir",
          "ke hulu kena bubu, ke hilir kena tengkalak",
          "ke hulu menongkah surut, ke hilir menongkah pasang",
          "ke mudik tentu hulunya, ke hilir tentu muaranya",
          "kundur tiada menjalar ke hulu, labu tiada menjalar ke hilir",
          "lebih baik menyesal di hulu riam, daripada menyesal di hilir riam",
          "menangis daun bangun-bangun hendak sama dengan hilir air",
          "mudik menyongsong arus, hilir menyongsong pasang",
          "sambil berdendang biduk hilir",
          "selama gagak hitam, selama air hilir",
          "seorang ke hilir, seorang ke mudik",
          "seperti biduk dikayuh hilir",
          "sudah terlalu hilir malam, apa hendak dikata lagi",
          "tak tentu hilir mudiknya",
          "tak terkayuhkan lagi biduk hilir",
          "tingkalak menghadap mudik, lukah menghadap hilir"
        ],
        "idiom": [],
        "peribahasa_dan_makna": [
          {
            "peribahasa": "belum tentu hilir mudiknya",
            "makna": ""
          },
          {
            "peribahasa": "bergalah hilir tertawa buaya, bersuluh di bulan terang tertawa harimau",
            "makna": ""
          },
          {
            "peribahasa": "berkata di bawah-bawah mandi di hilir-hilir",
            "makna": ""
          },
          {
            "peribahasa": "berkayuh sambil ke hilir",
            "makna": ""
          },
          {
            "peribahasa": "hilir malam mudik tak singgah, daun nipah dikatakan daun abu",
            "makna": ""
          },
          {
            "peribahasa": "ikan di hulu, tuba di hilir",
            "makna": ""
          },
          {
            "peribahasa": "ke hulu kena bubu, ke hilir kena tengkalak",
            "makna": ""
          },
          {
            "peribahasa": "ke hulu menongkah surut, ke hilir menongkah pasang",
            "makna": ""
          },
          {
            "peribahasa": "ke mudik tentu hulunya, ke hilir tentu muaranya",
            "makna": ""
          },
          {
            "peribahasa": "kundur tiada menjalar ke hulu, labu tiada menjalar ke hilir",
            "makna": ""
          },
          {
            "peribahasa": "lebih baik menyesal di hulu riam, daripada menyesal di hilir riam",
            "makna": ""
          },
          {
            "peribahasa": "menangis daun bangun-bangun hendak sama dengan hilir air",
            "makna": ""
          },
          {
            "peribahasa": "mudik menyongsong arus, hilir menyongsong pasang",
            "makna": ""
          },
          {
            "peribahasa": "sambil berdendang biduk hilir",
            "makna": ""
          },
          {
            "peribahasa": "selama gagak hitam, selama air hilir",
            "makna": ""
          },
          {
            "peribahasa": "seorang ke hilir, seorang ke mudik",
            "makna": ""
          },
          {
            "peribahasa": "seperti biduk dikayuh hilir",
            "makna": ""
          },
          {
            "peribahasa": "sudah terlalu hilir malam, apa hendak dikata lagi",
            "makna": ""
          },
          {
            "peribahasa": "tak tentu hilir mudiknya",
            "makna": ""
          },
          {
            "peribahasa": "tak terkayuhkan lagi biduk hilir",
            "makna": ""
          },
          {
            "peribahasa": "tingkalak menghadap mudik, lukah menghadap hilir",
            "makna": ""
          }
        ]
      }
    }
  ]
}