{
  "word": "dadih",
  "authenticated": true,
  "entries": [
    {
      "id": "17107",
      "nama": "da.dih",
      "nomor": "",
      "makna": [
        {
          "nomor": "1",
          "kelasKata": [
            {
              "kode": "n",
              "nama": "Nomina",
              "tipe": "kelas_kata"
            }
          ],
          "definisi": "air susu sapi, kerbau, dan sebagainya yang pekat atau dikentalkan",
          "contoh": []
        }
      ],
      "etimologi": {
        "text": "[Sanskerta दधि dadhi n net 'susu yang dikentalkan atau dibekukan']",
        "languages": [
          "Sanskerta"
        ]
      },
      "terkait": {
        "kataTurunan": [],
        "gabunganKata": [
          "dadih darah",
          "dadih jalang",
          "dadih kering",
          "dadih pekat"
        ],
        "peribahasa": [
          "mengajar orang tua makan dadih"
        ],
        "idiom": []
      }
    }
  ]
}