{
  "word": "oikumenis",
  "authenticated": true,
  "entries": [
    {
      "id": "21573",
      "nama": "oi.ku.me.nis",
      "nomor": "",
      "makna": [
        {
          "nomor": "1",
          "kelasKata": [
            {
              "kode": "a",
              "nama": "Adjektiva",
              "tipe": "kelas_kata"
            },
            {
              "kode": "Kris",
              "nama": "Agama Kristen",
              "tipe": "lainnya"
            }
          ],
          "definisi": "bersifat oikumene",
          "contoh": []
        }
      ]
    }
  ]
}