{
  "word": "cacat tubuh",
  "authenticated": true,
  "entries": [
    {
      "id": "14060",
      "nama": "cacat tubuh",
      "nomor": "",
      "makna": [
        {
          "nomor": "1",
          "kelasKata": [],
          "definisi": "kerusakan pada tubuh seseorang, baik badan maupun anggota badan, baik kehilangan fisik, ketidaknormalan bentuk maupun berkurangnya fungsi karena bawaan sejak lahir atau karena penyakit dan gangguan lain yang dialaminya sehingga timbul keterbatasan yang nyata untuk melaksanakan tugas hidup dan penyesuaian diri; tunadaksa",
          "contoh": []
        }
      ],
      "rootWord": "cacat",
      "terkait": {
        "kataTurunan": [],
        "gabunganKata": [],
        "peribahasa": [],
        "idiom": []
      }
    }
  ]
}