{"word":"cakup","authenticated":true,"entries":[{"id":"14288","nama":"ca.kup","nomor":"1","makna":[{"nomor":"1","kelasKata":[],"definisi":"⇢ Tesaurus  Etimologi: Jawa Kuno cakup Telusuri Selengkapnya  prakategorial mencakup, mencakup-cakup, pencakup, pencakupan","contoh":[]}],"etimologi":{"text":"[Jawa Kuno cakup 'memegang dengan tangan, menggenggam']","languages":["Jawa Kuno"]},"terkait":{"kataTurunan":["mencakup","mencakup-cakup","pencakup","pencakupan","cakup-mencakup","cakupan","ketercakupan","mencakupi","tercakup"],"gabunganKata":["cakup lindung"],"peribahasa":[],"idiom":[]}},{"id":"14292","nama":"ca.kup","nomor":"2","makna":[{"nomor":"1","kelasKata":[{"kode":"v","nama":"Verba","tipe":"kelas_kata"}],"definisi":"mencakup","contoh":[]}],"etimologi":{"text":"[Jawa Kuno cakup 'memegang dengan tangan, menggenggam']","languages":["Jawa Kuno"]},"terkait":{"kataTurunan":["cakup-mencakup","cakupan","ketercakupan","mencakup","mencakupi","tercakup"],"gabunganKata":["cakup lindung"],"peribahasa":[],"idiom":[]}}]}