{
  "word": "cengkol",
  "authenticated": true,
  "entries": [
    {
      "id": "15627",
      "nama": "ceng.kol",
      "nomor": "",
      "makna": [
        {
          "nomor": "1",
          "kelasKata": [
            {
              "kode": "a",
              "nama": "Adjektiva",
              "tipe": "kelas_kata"
            }
          ],
          "definisi": "pengkol",
          "contoh": []
        }
      ],
      "terkait": {
        "kataTurunan": [],
        "gabunganKata": [],
        "peribahasa": [],
        "idiom": []
      }
    }
  ]
}