{"word":"cilok","authenticated":true,"entries":[{"id":"16151","nama":"ci.lok","nomor":"12","makna":[{"nomor":"1","kelasKata":[],"definisi":"⇢ Tesaurus prakategorial mencilok, pencilok","contoh":[]}],"terkait":{"kataTurunan":["mencilok","pencilok"],"gabunganKata":["cilok goang"],"peribahasa":[],"idiom":[]}},{"id":"16154","nama":"ci.lok","nomor":"2","makna":[{"nomor":"1","kelasKata":[{"kode":"n","nama":"Nomina"},{"kode":"Sd","nama":"Sunda"},{"kode":"akr","nama":"akronim"}],"definisi":"penganan yang terbuat dari tapioka, bentuknya bulat menyerupai bakso, diberi isian gajih, daging, dan sebagainya, biasanya disajikan dengan saus, kecap, sambal kacang, dan sebagainya; aci dicolok","contoh":[]}],"terkait":{"kataTurunan":[],"gabunganKata":["cilok goang"],"peribahasa":[],"idiom":[]}}]}