{
  "word": "air alas",
  "authenticated": true,
  "entries": [
    {
      "id": "1166",
      "nama": "air alas",
      "nomor": "",
      "makna": [
        {
          "nomor": "1",
          "kelasKata": [],
          "definisi": "air masin",
          "contoh": []
        },
        {
          "nomor": "2",
          "kelasKata": [],
          "definisi": "air yang diletakkan pada tatakan untuk menghalau semut naik ke gelas",
          "contoh": []
        }
      ],
      "rootWord": "air",
      "terkait": {
        "kataTurunan": [],
        "gabunganKata": [],
        "peribahasa": [],
        "idiom": []
      }
    }
  ]
}