{
  "word": "aklimatisasi ketinggian",
  "authenticated": true,
  "entries": [
    {
      "id": "108648",
      "nama": "aklimatisasi ketinggian",
      "nomor": "",
      "makna": [
        {
          "nomor": "1",
          "kelasKata": [
            {
              "kode": "Olr",
              "nama": "Olahraga",
              "tipe": "lainnya"
            }
          ],
          "definisi": "latihan di dataran tinggi yang berguna untuk pernapasan atlet",
          "contoh": []
        }
      ],
      "rootWord": "aklimatisasi",
      "terkait": {
        "kataTurunan": [],
        "gabunganKata": [],
        "peribahasa": [],
        "idiom": []
      }
    }
  ]
}