{
  "word": "alih paket",
  "authenticated": true,
  "entries": [
    {
      "id": "102758",
      "nama": "alih paket",
      "nomor": "1",
      "makna": [
        {
          "nomor": "1",
          "kelasKata": [
            {
              "kode": "Komp",
              "nama": "Komputer",
              "tipe": "lainnya"
            }
          ],
          "definisi": "proses pengiriman informasi secara otomatis dari satu komputer di dalam jaringan ke komputer lainnya berupa pengalihan informasi dari satu saluran komunikasi ke saluran lainnya sampai dengan mencapai tujuan yang telah ditentukan",
          "contoh": []
        }
      ],
      "rootWord": "alih¹"
    }
  ]
}