{
  "word": "alun-alun",
  "authenticated": true,
  "entries": [
    {
      "id": "2654",
      "nama": "a.lun-a.lun",
      "nomor": "",
      "makna": [
        {
          "nomor": "1",
          "kelasKata": [
            {
              "kode": "n",
              "nama": "Nomina",
              "tipe": "kelas_kata"
            }
          ],
          "definisi": "tanah lapang yang luas di muka keraton atau di muka tempat kediaman resmi bupati, dan sebagainya",
          "contoh": []
        }
      ],
      "etimologi": {
        "text": "[Jawa Kuno alun-alun 'lapangan persegi di depan istana, alun-alun']",
        "languages": [
          "Jawa Kuno"
        ]
      }
    }
  ]
}