{
  "word": "ibu baptis",
  "authenticated": true,
  "entries": [
    {
      "id": "206399",
      "nama": "ibu baptis",
      "nomor": "",
      "makna": [
        {
          "nomor": "1",
          "kelasKata": [
            {
              "kode": "Kris",
              "nama": "Agama Kristen",
              "tipe": "lainnya"
            }
          ],
          "definisi": "wanita yang bertindak sebagai pelindung pada waktu upacara pembaptisan; ibu permandian",
          "contoh": []
        }
      ],
      "rootWord": "ibu",
      "terkait": {
        "kataTurunan": [],
        "gabunganKata": [],
        "peribahasa": [],
        "idiom": []
      }
    }
  ]
}