{
  "word": "impromptu",
  "authenticated": true,
  "entries": [
    {
      "id": "97334",
      "nama": "impromptu",
      "nomor": "",
      "makna": [
        {
          "nomor": "1",
          "kelasKata": [
            {
              "kode": "ukp",
              "nama": "Ungkapan",
              "tipe": "kelas_kata"
            },
            {
              "kode": "Pr",
              "nama": "Prancis",
              "tipe": "lainnya"
            }
          ],
          "definisi": "dibuat atau dilakukan tanpa persiapan atau secara spontan",
          "contoh": []
        }
      ],
      "terkait": {
        "kataTurunan": [],
        "gabunganKata": [],
        "peribahasa": [],
        "idiom": []
      }
    }
  ]
}