{
  "word": "sahang",
  "authenticated": true,
  "entries": [
    {
      "id": "70922",
      "nama": "sa.hang",
      "nomor": "",
      "makna": [
        {
          "nomor": "1",
          "kelasKata": [
            {
              "kode": "n",
              "nama": "Nomina",
              "tipe": "kelas_kata"
            }
          ],
          "definisi": "lada; merica",
          "contoh": [
            {
              "nomor": 2,
              "teks": "ia membawa pala, cengkih, dan --"
            }
          ]
        }
      ],
      "terkait": {
        "kataTurunan": [],
        "gabunganKata": [
          "sahang tahi burung"
        ],
        "peribahasa": [],
        "idiom": []
      }
    },
    {
      "id": "277595",
      "nama": "sa.hang",
      "nomor": "1",
      "makna": [
        {
          "nomor": "1",
          "kelasKata": [
            {
              "kode": "n",
              "nama": "Nomina",
              "tipe": "kelas_kata"
            }
          ],
          "definisi": "wadah panjang yang dibuat dari bambu, kayu ukir, tanduk hewan, atau bahan lain yang mudah ditemukan di sekitar rumah, digunakan sebagai tempat penyimpan obat-obatan oleh suku Batak Karo",
          "contoh": []
        }
      ]
    }
  ]
}