{
  "word": "seorang makan nangka, semua kena getahnya",
  "authenticated": true,
  "entries": [
    {
      "id": "56346",
      "nama": "seorang makan nangka, semua kena getahnya",
      "nomor": "",
      "makna": [
        {
          "nomor": "1",
          "kelasKata": [],
          "definisi": "seorang yang berbuat kesalahan demi memenuhi kesenangannya, tetapi orang lain turut menanggung akibatnya",
          "contoh": []
        }
      ],
      "jenis": "peribahasa",
      "rootWord": "nangka",
      "terkait": {
        "kataTurunan": [],
        "gabunganKata": [],
        "peribahasa": [],
        "idiom": []
      }
    }
  ]
}