{
  "word": "slintat-slintut",
  "authenticated": true,
  "entries": [
    {
      "id": "78156",
      "nama": "slin.tat-slin.tut",
      "nomor": "",
      "makna": [
        {
          "nomor": "1",
          "kelasKata": [
            {
              "kode": "adv",
              "nama": "Adverbia",
              "tipe": "kelas_kata"
            },
            {
              "kode": "Jw",
              "nama": "Jawa",
              "tipe": "bahasa"
            }
          ],
          "definisi": "sembunyi-sembunyi",
          "contoh": []
        }
      ]
    }
  ]
}