{
  "word": "spektrum magnetik",
  "authenticated": true,
  "entries": [
    {
      "id": "78640",
      "nama": "spektrum magnetik",
      "nomor": "",
      "makna": [
        {
          "nomor": "1",
          "kelasKata": [],
          "definisi": "garis gaya dari suatu medan magnetik yang diperagakan oleh serbuk besi di atas permukaan datar",
          "contoh": []
        }
      ],
      "rootWord": "spektrum",
      "terkait": {
        "kataTurunan": [],
        "gabunganKata": [],
        "peribahasa": [],
        "idiom": []
      }
    }
  ]
}