{
  "word": "batik tiga negeri",
  "authenticated": true,
  "entries": [
    {
      "id": "170132",
      "nama": "batik tiga negeri",
      "nomor": "",
      "makna": [
        {
          "nomor": "1",
          "kelasKata": [],
          "definisi": "batik yang proses pewarnaannya dilakukan di tiga daerah, yakni Lasem untuk warna merah, Solo atau Yogyakarta untuk warna cokelat, dan Pekalongan untuk warna biru, umumnya bermotif buketan",
          "contoh": []
        }
      ],
      "rootWord": "batik",
      "terkait": {
        "kataTurunan": [],
        "gabunganKata": [],
        "peribahasa": [],
        "idiom": []
      }
    }
  ]
}