{
  "word": "benih",
  "authenticated": true,
  "entries": [
    {
      "id": "10272",
      "nama": "be.nih",
      "nomor": "",
      "makna": [
        {
          "nomor": "1",
          "kelasKata": [
            {
              "kode": "n",
              "nama": "Nomina",
              "tipe": "kelas_kata"
            }
          ],
          "definisi": "biji atau buah yang disediakan untuk ditanam atau disemaikan",
          "contoh": [
            {
              "nomor": 2,
              "teks": "yang akan dijadikan -- haruslah buah yang baik dan cukup tua"
            }
          ]
        },
        {
          "nomor": "2",
          "kelasKata": [
            {
              "kode": "n",
              "nama": "Nomina",
              "tipe": "kelas_kata"
            }
          ],
          "definisi": "bibit atau semaian yang akan ditanam",
          "contoh": [
            {
              "nomor": 2,
              "teks": "-- cengkih itu sebaiknya dipindahkan setelah setengah meter tingginya"
            }
          ]
        },
        {
          "nomor": "3",
          "kelasKata": [
            {
              "kode": "n",
              "nama": "Nomina",
              "tipe": "kelas_kata"
            }
          ],
          "definisi": "sperma untuk bibit pengembangbiakan ternak dan sebagainya",
          "contoh": [
            {
              "nomor": 2,
              "teks": "-- sapi pejantan unggul dapat disimpan lama di tempat yang bersuhu dingin"
            }
          ]
        },
        {
          "nomor": "4",
          "kelasKata": [
            {
              "kode": "n",
              "nama": "Nomina",
              "tipe": "kelas_kata"
            }
          ],
          "definisi": "sesuatu yang menjadi sebab; asal mula",
          "contoh": [
            {
              "nomor": 2,
              "teks": "ucapan yang kasar dapat menjadi -- perkelahian"
            }
          ]
        },
        {
          "nomor": "5",
          "kelasKata": [
            {
              "kode": "n",
              "nama": "Nomina",
              "tipe": "kelas_kata"
            }
          ],
          "definisi": "keturunan; turunan; asal",
          "contoh": []
        },
        {
          "nomor": "6",
          "kelasKata": [
            {
              "kode": "n",
              "nama": "Nomina",
              "tipe": "kelas_kata"
            }
          ],
          "definisi": "sesuatu yang akan tumbuh atau akan menjadi",
          "contoh": [
            {
              "nomor": 2,
              "teks": "-- penyakit cacar"
            }
          ]
        }
      ],
      "terkait": {
        "kataTurunan": [
          "berbenih",
          "membenihkan",
          "pembenih",
          "pembenihan",
          "perbenihan"
        ],
        "gabunganKata": [
          "benih asalan",
          "benih benar",
          "benih bersertifikat",
          "benih bersih",
          "benih bina",
          "benih cinta",
          "benih dasar",
          "benih firman",
          "benih ikan",
          "benih kebaikan",
          "benih kebencian",
          "benih murni",
          "benih ortodoks",
          "benih padi",
          "benih rekalsitran",
          "benih sehat",
          "benih sumber",
          "benih unggul"
        ],
        "peribahasa": [
          "ada tugal ada benih",
          "asal ditugal, ada lah benih",
          "asal menugal, adalah benih",
          "benih yang baik tak memilih tanah",
          "jika benih yang baik jatuh ke laut, menjadi pulau"
        ],
        "idiom": [],
        "peribahasa_dan_makna": [
          {
            "peribahasa": "ada tugal ada benih",
            "makna": "Menggambarkan bahwa setiap usaha atau pekerjaan yang dilakukan akan selalu ada hasilnya, meskipun kecil."
          },
          {
            "peribahasa": "asal ditugal, ada lah benih",
            "makna": "Menyiratkan bahwa setiap tindakan atau upaya yang dilakukan, sekecil apa pun, akan selalu menghasilkan sesuatu, baik atau buruk."
          },
          {
            "peribahasa": "asal menugal, adalah benih",
            "makna": "Sama dengan peribahasa sebelumnya, menekankan bahwa setiap pekerjaan yang dimulai akan selalu ada hasilnya, meskipun tidak selalu sesuai harapan."
          },
          {
            "peribahasa": "benih yang baik tak memilih tanah",
            "makna": "Menggambarkan bahwa orang yang memiliki kualitas atau karakter baik akan tetap menunjukkan kebaikan dan keberhasilan di mana pun ia berada, tanpa terpengaruh oleh lingkungan."
          },
          {
            "peribahasa": "jika benih yang baik jatuh ke laut, menjadi pulau",
            "makna": "Menekankan bahwa orang yang memiliki kualitas unggul atau potensi besar akan selalu berhasil dan memberikan dampak positif di mana pun ia ditempatkan, bahkan dalam kondisi yang paling sulit sekalipun."
          }
        ]
      }
    }
  ]
}