{
  "word": "berbayang",
  "authenticated": true,
  "entries": [
    {
      "id": "9119",
      "nama": "ber.ba.yang",
      "nomor": "1",
      "makna": [
        {
          "nomor": "1",
          "kelasKata": [
            {
              "kode": "v",
              "nama": "Verba",
              "tipe": "kelas_kata"
            }
          ],
          "definisi": "ada bayang-bayangnya",
          "contoh": [
            {
              "nomor": 2,
              "teks": "kata orang, harimau jadi-jadian itu tidak ~"
            }
          ]
        },
        {
          "nomor": "2",
          "kelasKata": [
            {
              "kode": "v",
              "nama": "Verba",
              "tipe": "kelas_kata"
            }
          ],
          "definisi": "seakan-akan kelihatan dalam angan-angan",
          "contoh": [
            {
              "nomor": 2,
              "teks": "hal itu tidak nyata, tetapi ~ pada ingatan saya"
            }
          ]
        }
      ],
      "rootWord": "bayang¹",
      "terkait": {
        "kataTurunan": [],
        "gabunganKata": [],
        "peribahasa": [],
        "idiom": []
      }
    }
  ]
}