{
  "word": "berkongsi",
  "authenticated": true,
  "entries": [
    {
      "id": "43175",
      "nama": "ber.kong.si",
      "nomor": "",
      "makna": [
        {
          "nomor": "1",
          "kelasKata": [
            {
              "kode": "v",
              "nama": "Verba",
              "tipe": "kelas_kata"
            }
          ],
          "definisi": "mengadakan persekutuan dagang (dengan)",
          "contoh": []
        },
        {
          "nomor": "2",
          "kelasKata": [
            {
              "kode": "v",
              "nama": "Verba",
              "tipe": "kelas_kata"
            }
          ],
          "definisi": "bersekutu; berkomplot",
          "contoh": []
        }
      ],
      "rootWord": "kongsi"
    }
  ]
}