{
  "word": "bermenung",
  "authenticated": true,
  "entries": [
    {
      "id": "53688",
      "nama": "ber.me.nung",
      "nomor": "",
      "makna": [
        {
          "nomor": "1",
          "kelasKata": [
            {
              "kode": "v",
              "nama": "Verba",
              "tipe": "kelas_kata"
            }
          ],
          "definisi": "diam sambil berpikir dalam-dalam; tepekur",
          "contoh": [
            {
              "nomor": 2,
              "teks": "dia duduk ~ memikirkan rencana kepergiannya ke tanah suci"
            }
          ]
        }
      ],
      "rootWord": "menung"
    }
  ]
}