{
  "word": "biner",
  "authenticated": true,
  "entries": [
    {
      "id": "11606",
      "nama": "bi.ner",
      "nomor": "",
      "makna": [
        {
          "nomor": "1",
          "kelasKata": [
            {
              "kode": "a",
              "nama": "Adjektiva",
              "tipe": "kelas_kata"
            }
          ],
          "definisi": "terjadi dari atau ditandai oleh dua benda atau dua bagian; serba dua",
          "contoh": []
        },
        {
          "nomor": "2",
          "kelasKata": [
            {
              "kode": "a",
              "nama": "Adjektiva",
              "tipe": "kelas_kata"
            },
            {
              "kode": "Mat",
              "nama": "Matematika",
              "tipe": "bidang_subjek"
            }
          ],
          "definisi": "berdasar dua (tentang bilangan pada sistem bilangan)",
          "contoh": []
        }
      ]
    }
  ]
}